pydatamailbox/__init__.py
pydatamailbox/client.py
pydatamailbox/exceptions.py
pydatamailbox-0.2.3.dist-info/AUTHORS.md
pydatamailbox-0.2.3.dist-info/LICENSE
pydatamailbox-0.2.3.dist-info/METADATA
pydatamailbox-0.2.3.dist-info/WHEEL
pydatamailbox-0.2.3.dist-info/top_level.txt
pydatamailbox-0.2.3.dist-info/RECORD
