Metadata-Version: 2.1
Name: pydatamailbox
Version: 0.2.3
Summary: Unofficial client for the Ewon's datamailbox web APIs
Home-page: https://github.com/optimdata/pydatamailbox
Author: Guillaume Thomas
Author-email: guillaume.thomas@inuse.eu
License: MIT license
Keywords: pydatamailbox
Platform: UNKNOWN
Classifier: Development Status :: 2 - Pre-Alpha
Classifier: Intended Audience :: Developers
Classifier: License :: OSI Approved :: MIT License
Classifier: Natural Language :: English
Classifier: Programming Language :: Python :: 3
Classifier: Programming Language :: Python :: 3.6
Classifier: Programming Language :: Python :: 3.7
License-File: LICENSE
License-File: AUTHORS.md
